{"notes_list": [
	{"id": "1", "sec": "", "type": "100", "startPos": "", "finishPos": "", "status": "103", "sync": "0", "groupId": "0"},
	{"id": "2", "sec": "0", "type": "91", "startPos": "", "finishPos": "", "status": "0", "sync": "0", "groupId": "0"},
	{"id": "3", "sec": "2.742857143", "type": "1", "startPos": "5", "finishPos": "5", "status": "0", "sync": "0", "groupId": "0"},
	{"id": "4", "sec": "4.114285714", "type": "1", "startPos": "4", "finishPos": "4", "status": "0", "sync": "0", "groupId": "0"},
	{"id": "5", "sec": "5.485714286", "type": "1", "startPos": "2", "finishPos": "2", "status": "0", "sync": "0", "groupId": "0"},
	{"id": "6", "sec": "6.857142857", "type": "1", "startPos": "1", "finishPos": "1", "status": "0", "sync": "0", "groupId": "0"},
	{"id": "7", "sec": "8.228571429", "type": "1", "startPos": "2", "finishPos": "2", "status": "0", "sync": "0", "groupId": "0"},
	{"id": "8", "sec": "9.6", "type": "1", "startPos": "4", "finishPos": "4", "status": "0", "sync": "0", "groupId": "0"},
	{"id": "9", "sec": "10.97142857", "type": "1", "startPos": "3", "finishPos": "3", "status": "0", "sync": "0", "groupId": "0"},
	{"id": "10", "sec": "11.65714286", "type": "1", "startPos": "3", "finishPos": "3", "status": "0", "sync": "0", "groupId": "0"},
	{"id": "11", "sec": "12.34285714", "type": "1", "startPos": "3", "finishPos": "3", "status": "0", "sync": "0", "groupId": "0"},
	{"id": "12", "sec": "13.71428571", "type": "1", "startPos": "2", "finishPos": "2", "status": "0", "sync": "1", "groupId": "0"},
	{"id": "13", "sec": "13.71428571", "type": "1", "startPos": "4", "finishPos": "4", "status": "0", "sync": "1", "groupId": "0"},
	{"id": "14", "sec": "16.45714286", "type": "1", "startPos": "1", "finishPos": "3", "status": "0", "sync": "0", "groupId": "0"},
	{"id": "15", "sec": "19.2", "type": "1", "startPos": "4", "finishPos": "4", "status": "0", "sync": "0", "groupId": "0"},
	{"id": "16", "sec": "20.57142857", "type": "1", "startPos": "2", "finishPos": "2", "status": "0", "sync": "0", "groupId": "0"},
	{"id": "17", "sec": "21.94285714", "type": "1", "startPos": "4", "finishPos": "4", "status": "0", "sync": "0", "groupId": "0"},
	{"id": "18", "sec": "23.31428571", "type": "1", "startPos": "2", "finishPos": "2", "status": "0", "sync": "0", "groupId": "0"},
	{"id": "19", "sec": "24.68571429", "type": "1", "startPos": "5", "finishPos": "5", "status": "0", "sync": "0", "groupId": "0"},
	{"id": "20", "sec": "26.05714286", "type": "1", "startPos": "2", "finishPos": "2", "status": "0", "sync": "0", "groupId": "0"},
	{"id": "21", "sec": "27.42857143", "type": "1", "startPos": "4", "finishPos": "4", "status": "0", "sync": "0", "groupId": "0"},
	{"id": "22", "sec": "28.97142857", "type": "1", "startPos": "3", "finishPos": "3", "status": "0", "sync": "0", "groupId": "0"},
	{"id": "23", "sec": "29.31428571", "type": "1", "startPos": "3", "finishPos": "3", "status": "0", "sync": "0", "groupId": "0"},
	{"id": "24", "sec": "30.17142857", "type": "1", "startPos": "2", "finishPos": "2", "status": "0", "sync": "0", "groupId": "0"},
	{"id": "25", "sec": "31.54285714", "type": "1", "startPos": "4", "finishPos": "4", "status": "0", "sync": "0", "groupId": "0"},
	{"id": "26", "sec": "32.91428571", "type": "1", "startPos": "5", "finishPos": "5", "status": "0", "sync": "0", "groupId": "0"},
	{"id": "27", "sec": "34.28571429", "type": "1", "startPos": "2", "finishPos": "2", "status": "0", "sync": "0", "groupId": "0"},
	{"id": "28", "sec": "35.65714286", "type": "1", "startPos": "4", "finishPos": "4", "status": "0", "sync": "0", "groupId": "0"},
	{"id": "29", "sec": "37.02857143", "type": "1", "startPos": "4", "finishPos": "4", "status": "0", "sync": "0", "groupId": "0"},
	{"id": "30", "sec": "38.4", "type": "1", "startPos": "2", "finishPos": "2", "status": "0", "sync": "0", "groupId": "0"},
	{"id": "31", "sec": "39.6", "type": "1", "startPos": "3", "finishPos": "3", "status": "0", "sync": "0", "groupId": "0"},
	{"id": "32", "sec": "39.94285714", "type": "1", "startPos": "3", "finishPos": "3", "status": "0", "sync": "0", "groupId": "0"},
	{"id": "33", "sec": "40.28571429", "type": "1", "startPos": "3", "finishPos": "3", "status": "0", "sync": "0", "groupId": "0"},
	{"id": "34", "sec": "40.8", "type": "1", "startPos": "2", "finishPos": "2", "status": "0", "sync": "0", "groupId": "0"},
	{"id": "35", "sec": "41.14285714", "type": "2", "startPos": "2", "finishPos": "2", "status": "0", "sync": "0", "groupId": "0"},
	{"id": "36", "sec": "46.62857143", "type": "2", "startPos": "2", "finishPos": "2", "status": "0", "sync": "0", "groupId": "0"},
	{"id": "37", "sec": "48.34285714", "type": "1", "startPos": "1", "finishPos": "1", "status": "0", "sync": "0", "groupId": "0"},
	{"id": "38", "sec": "49.37142857", "type": "1", "startPos": "4", "finishPos": "4", "status": "0", "sync": "0", "groupId": "0"},
	{"id": "39", "sec": "50.05714286", "type": "1", "startPos": "4", "finishPos": "4", "status": "0", "sync": "0", "groupId": "0"},
	{"id": "40", "sec": "50.74285714", "type": "1", "startPos": "2", "finishPos": "2", "status": "0", "sync": "0", "groupId": "0"},
	{"id": "41", "sec": "51.25714286", "type": "1", "startPos": "2", "finishPos": "2", "status": "0", "sync": "0", "groupId": "0"},
	{"id": "42", "sec": "51.77142857", "type": "1", "startPos": "4", "finishPos": "4", "status": "0", "sync": "0", "groupId": "0"},
	{"id": "43", "sec": "53.14185714", "type": "81", "startPos": "", "finishPos": "", "status": "0", "sync": "0", "groupId": "0"},
	{"id": "44", "sec": "53.14285714", "type": "1", "startPos": "2", "finishPos": "2", "status": "0", "sync": "0", "groupId": "0"},
	{"id": "45", "sec": "53.48571429", "type": "1", "startPos": "5", "finishPos": "5", "status": "0", "sync": "0", "groupId": "0"},
	{"id": "46", "sec": "54.17142857", "type": "1", "startPos": "5", "finishPos": "5", "status": "0", "sync": "0", "groupId": "0"},
	{"id": "47", "sec": "54.85714286", "type": "1", "startPos": "4", "finishPos": "4", "status": "0", "sync": "0", "groupId": "0"},
	{"id": "48", "sec": "55.54285714", "type": "1", "startPos": "4", "finishPos": "4", "status": "0", "sync": "0", "groupId": "0"},
	{"id": "49", "sec": "56.22857143", "type": "2", "startPos": "2", "finishPos": "2", "status": "0", "sync": "0", "groupId": "0"},
	{"id": "50", "sec": "57.6", "type": "2", "startPos": "2", "finishPos": "2", "status": "0", "sync": "0", "groupId": "0"},
	{"id": "51", "sec": "58.97142857", "type": "1", "startPos": "5", "finishPos": "5", "status": "0", "sync": "0", "groupId": "0"},
	{"id": "52", "sec": "59.65714286", "type": "1", "startPos": "4", "finishPos": "4", "status": "0", "sync": "0", "groupId": "0"},
	{"id": "53", "sec": "60.34285714", "type": "1", "startPos": "4", "finishPos": "4", "status": "0", "sync": "0", "groupId": "0"},
	{"id": "54", "sec": "61.71428571", "type": "1", "startPos": "1", "finishPos": "1", "status": "0", "sync": "0", "groupId": "0"},
	{"id": "55", "sec": "63.08571429", "type": "1", "startPos": "4", "finishPos": "4", "status": "0", "sync": "0", "groupId": "0"},
	{"id": "56", "sec": "64.45714286", "type": "1", "startPos": "5", "finishPos": "5", "status": "0", "sync": "0", "groupId": "0"},
	{"id": "57", "sec": "65.14285714", "type": "1", "startPos": "5", "finishPos": "5", "status": "0", "sync": "0", "groupId": "0"},
	{"id": "58", "sec": "65.82857143", "type": "1", "startPos": "4", "finishPos": "4", "status": "0", "sync": "0", "groupId": "0"},
	{"id": "59", "sec": "66.51428571", "type": "1", "startPos": "4", "finishPos": "4", "status": "0", "sync": "0", "groupId": "0"},
	{"id": "60", "sec": "67.2", "type": "2", "startPos": "5", "finishPos": "5", "status": "0", "sync": "0", "groupId": "0"},
	{"id": "61", "sec": "68.57142857", "type": "2", "startPos": "5", "finishPos": "5", "status": "0", "sync": "0", "groupId": "0"},
	{"id": "62", "sec": "69.94285714", "type": "1", "startPos": "2", "finishPos": "2", "status": "0", "sync": "0", "groupId": "0"},
	{"id": "63", "sec": "71.31428571", "type": "1", "startPos": "5", "finishPos": "5", "status": "0", "sync": "0", "groupId": "0"},
	{"id": "64", "sec": "72.68571429", "type": "1", "startPos": "4", "finishPos": "4", "status": "0", "sync": "0", "groupId": "0"},
	{"id": "65", "sec": "73.37142857", "type": "1", "startPos": "2", "finishPos": "2", "status": "0", "sync": "0", "groupId": "0"},
	{"id": "66", "sec": "74.05714286", "type": "1", "startPos": "4", "finishPos": "4", "status": "0", "sync": "0", "groupId": "0"},
	{"id": "67", "sec": "75.42857143", "type": "1", "startPos": "4", "finishPos": "4", "status": "0", "sync": "1", "groupId": "0"},
	{"id": "68", "sec": "75.42857143", "type": "1", "startPos": "2", "finishPos": "2", "status": "0", "sync": "1", "groupId": "0"},
	{"id": "69", "sec": "75.42957143", "type": "82", "startPos": "", "finishPos": "", "status": "0", "sync": "0", "groupId": "0"},
	{"id": "70", "sec": "78.17142857", "type": "1", "startPos": "1", "finishPos": "3", "status": "0", "sync": "0", "groupId": "0"},
	{"id": "71", "sec": "82.28571429", "type": "2", "startPos": "5", "finishPos": "5", "status": "0", "sync": "0", "groupId": "0"},
	{"id": "72", "sec": "87.08571429", "type": "2", "startPos": "5", "finishPos": "5", "status": "0", "sync": "0", "groupId": "0"},
	{"id": "73", "sec": "87.77142857", "type": "2", "startPos": "1", "finishPos": "1", "status": "0", "sync": "0", "groupId": "0"},
	{"id": "74", "sec": "89.82857143", "type": "2", "startPos": "1", "finishPos": "1", "status": "0", "sync": "0", "groupId": "0"},
	{"id": "75", "sec": "90.51428571", "type": "1", "startPos": "2", "finishPos": "2", "status": "0", "sync": "0", "groupId": "0"},
	{"id": "76", "sec": "91.88571429", "type": "1", "startPos": "4", "finishPos": "4", "status": "0", "sync": "0", "groupId": "0"},
	{"id": "77", "sec": "93.25714286", "type": "1", "startPos": "5", "finishPos": "5", "status": "0", "sync": "0", "groupId": "0"},
	{"id": "78", "sec": "93.94285714", "type": "1", "startPos": "5", "finishPos": "5", "status": "0", "sync": "0", "groupId": "0"},
	{"id": "79", "sec": "94.62857143", "type": "1", "startPos": "4", "finishPos": "4", "status": "0", "sync": "0", "groupId": "0"},
	{"id": "80", "sec": "95.31428571", "type": "1", "startPos": "4", "finishPos": "4", "status": "0", "sync": "0", "groupId": "0"},
	{"id": "81", "sec": "96", "type": "2", "startPos": "2", "finishPos": "2", "status": "0", "sync": "0", "groupId": "0"},
	{"id": "82", "sec": "98.05714286", "type": "2", "startPos": "2", "finishPos": "2", "status": "0", "sync": "0", "groupId": "0"},
	{"id": "83", "sec": "98.74285714", "type": "1", "startPos": "1", "finishPos": "1", "status": "0", "sync": "0", "groupId": "0"},
	{"id": "84", "sec": "100.1142857", "type": "1", "startPos": "5", "finishPos": "5", "status": "0", "sync": "0", "groupId": "0"},
	{"id": "85", "sec": "101.4857143", "type": "1", "startPos": "4", "finishPos": "4", "status": "0", "sync": "0", "groupId": "0"},
	{"id": "86", "sec": "102.1714286", "type": "1", "startPos": "4", "finishPos": "4", "status": "0", "sync": "0", "groupId": "0"},
	{"id": "87", "sec": "102.8571429", "type": "1", "startPos": "4", "finishPos": "4", "status": "0", "sync": "0", "groupId": "0"},
	{"id": "88", "sec": "104.2275714", "type": "81", "startPos": "", "finishPos": "", "status": "0", "sync": "0", "groupId": "0"},
	{"id": "89", "sec": "104.2285714", "type": "1", "startPos": "5", "finishPos": "5", "status": "0", "sync": "0", "groupId": "0"},
	{"id": "90", "sec": "104.9142857", "type": "1", "startPos": "5", "finishPos": "5", "status": "0", "sync": "0", "groupId": "0"},
	{"id": "91", "sec": "105.6", "type": "1", "startPos": "4", "finishPos": "4", "status": "0", "sync": "0", "groupId": "0"},
	{"id": "92", "sec": "106.2857143", "type": "1", "startPos": "4", "finishPos": "4", "status": "0", "sync": "0", "groupId": "0"},
	{"id": "93", "sec": "106.9714286", "type": "1", "startPos": "2", "finishPos": "2", "status": "0", "sync": "0", "groupId": "0"},
	{"id": "94", "sec": "107.4857143", "type": "1", "startPos": "2", "finishPos": "2", "status": "0", "sync": "0", "groupId": "0"},
	{"id": "95", "sec": "108", "type": "2", "startPos": "5", "finishPos": "5", "status": "0", "sync": "0", "groupId": "0"},
	{"id": "96", "sec": "109.0285714", "type": "2", "startPos": "5", "finishPos": "5", "status": "0", "sync": "0", "groupId": "0"},
	{"id": "97", "sec": "109.7142857", "type": "1", "startPos": "1", "finishPos": "1", "status": "0", "sync": "0", "groupId": "0"},
	{"id": "98", "sec": "111.0857143", "type": "1", "startPos": "3", "finishPos": "5", "status": "0", "sync": "0", "groupId": "0"},
	{"id": "99", "sec": "112.4571429", "type": "1", "startPos": "5", "finishPos": "4", "status": "0", "sync": "1", "groupId": "0"},
	{"id": "100", "sec": "112.4571429", "type": "1", "startPos": "1", "finishPos": "2", "status": "0", "sync": "1", "groupId": "0"},
	{"id": "101", "sec": "113.1428571", "type": "1", "startPos": "4", "finishPos": "4", "status": "0", "sync": "1", "groupId": "0"},
	{"id": "102", "sec": "113.1428571", "type": "1", "startPos": "2", "finishPos": "2", "status": "0", "sync": "1", "groupId": "0"},
	{"id": "103", "sec": "113.8285714", "type": "1", "startPos": "3", "finishPos": "4", "status": "0", "sync": "1", "groupId": "0"},
	{"id": "104", "sec": "113.8285714", "type": "1", "startPos": "3", "finishPos": "2", "status": "0", "sync": "1", "groupId": "0"},
	{"id": "105", "sec": "115.2", "type": "1", "startPos": "1", "finishPos": "1", "status": "0", "sync": "0", "groupId": "0"},
	{"id": "106", "sec": "115.8857143", "type": "1", "startPos": "5", "finishPos": "5", "status": "0", "sync": "0", "groupId": "0"},
	{"id": "107", "sec": "116.5714286", "type": "2", "startPos": "3", "finishPos": "3", "status": "0", "sync": "0", "groupId": "0"},
	{"id": "108", "sec": "118.9714286", "type": "2", "startPos": "3", "finishPos": "3", "status": "0", "sync": "0", "groupId": "0"},
	{"id": "109", "sec": "118.9724286", "type": "82", "startPos": "", "finishPos": "", "status": "0", "sync": "0", "groupId": "0"},
	{"id": "110", "sec": "123.4285714", "type": "92", "startPos": "", "finishPos": "", "status": "0", "sync": "0", "groupId": "0"}	]}