{"notes_list": [
	{"time": "0.00 ", "lyrics": "", "size": ""},
	{"time": "16.000 ", "lyrics": "草かき分け歩き続けたこの道が全てだったから", "size": ""},
	{"time": "28.510 ", "lyrics": "本当の自分をさらけ出すのは怖かった", "size": ""},
	{"time": "38.860 ", "lyrics": "だけどあの日あなたと出会い笑顔に触れ心は溶けて", "size": ""},
	{"time": "51.340 ", "lyrics": "こんなに自分が優しくなれるとは思わなかった", "size": ""},
	{"time": "62.790 ", "lyrics": "あったかい夢の前で", "size": ""},
	{"time": "68.490 ", "lyrics": "何も言えはしないけど", "size": ""},
	{"time": "74.200 ", "lyrics": "あいくるしい人に会えたから", "size": ""},
	{"time": "79.920 ", "lyrics": "永遠を確かめるように背中を見つめてみた", "size": ""},
	{"time": "90.650 ", "lyrics": "急になんか正解の風に流されたような", "size": ""},
	{"time": "102.617", "lyrics": "私の願いなんて単純なものだよ", "size": ""},
	{"time": "107.759", "lyrics": "いつも通りに", "size": ""},
	{"time": "113.558", "lyrics": "", "size": ""}	]}